{
  "task_id": "2.1",
  "title_ru": "Производственный участок",
  "input_snapshot": {
    "machine_count": 41,
    "tc_minutes": 105,
    "ts_minutes": 46,
    "arrival_rate_per_minute": 0.009523809523809525,
    "service_rate_per_minute": 0.021739130434782608,
    "offered_load_per_machine_erlangs": 0.4380952380952381
  },
  "metadata": {
    "solver_kind": "analytical",
    "formula_family": "birth-death finite-source",
    "uses_truncation": false,
    "truncation_policy": null
  },
  "sweeps": [
    {
      "task_id": "2.1",
      "model": "machine-repairman finite-source",
      "x_axis": "repairers",
      "fixed_parameters": {},
      "points": [
        {
          "x_value": 1,
          "status": "ok",
          "regime": {
            "status": "ok",
            "is_stationary": true,
            "reason": null
          },
          "metrics": {
            "idle_machines_expected": 38.71739130434783,
            "waiting_machines_expected": 37.71739130434783,
            "waiting_probability": 1.0,
            "busy_repairers_expected": 1.0,
            "repairers_utilization": 1.0
          },
          "fixed_parameters": {},
          "truncation": null,
          "diagnostics": {
            "queue_exists_probability_state": 1.0,
            "waiting_probability_interpretation": "arrival_weighted_probability_for_new_breakdown"
          }
        },
        {
          "x_value": 2,
          "status": "ok",
          "regime": {
            "status": "ok",
            "is_stationary": true,
            "reason": null
          },
          "metrics": {
            "idle_machines_expected": 36.434782608695656,
            "waiting_machines_expected": 34.434782608695656,
            "waiting_probability": 1.0,
            "busy_repairers_expected": 2.0,
            "repairers_utilization": 1.0
          },
          "fixed_parameters": {},
          "truncation": null,
          "diagnostics": {
            "queue_exists_probability_state": 1.0,
            "waiting_probability_interpretation": "arrival_weighted_probability_for_new_breakdown"
          }
        },
        {
          "x_value": 3,
          "status": "ok",
          "regime": {
            "status": "ok",
            "is_stationary": true,
            "reason": null
          },
          "metrics": {
            "idle_machines_expected": 34.15217391304348,
            "waiting_machines_expected": 31.15217391304348,
            "waiting_probability": 0.9999999999999999,
            "busy_repairers_expected": 3.0,
            "repairers_utilization": 1.0
          },
          "fixed_parameters": {},
          "truncation": null,
          "diagnostics": {
            "queue_exists_probability_state": 0.9999999999999999,
            "waiting_probability_interpretation": "arrival_weighted_probability_for_new_breakdown"
          }
        },
        {
          "x_value": 4,
          "status": "ok",
          "regime": {
            "status": "ok",
            "is_stationary": true,
            "reason": null
          },
          "metrics": {
            "idle_machines_expected": 31.86956521739342,
            "waiting_machines_expected": 27.869565217394342,
            "waiting_probability": 0.9999999999967323,
            "busy_repairers_expected": 3.999999999999076,
            "repairers_utilization": 0.999999999999769
          },
          "fixed_parameters": {},
          "truncation": null,
          "diagnostics": {
            "queue_exists_probability_state": 0.9999999999965014,
            "waiting_probability_interpretation": "arrival_weighted_probability_for_new_breakdown"
          }
        },
        {
          "x_value": 5,
          "status": "ok",
          "regime": {
            "status": "ok",
            "is_stationary": true,
            "reason": null
          },
          "metrics": {
            "idle_machines_expected": 29.58695652570653,
            "waiting_machines_expected": 24.586956527444627,
            "waiting_probability": 0.9999999955110065,
            "busy_repairers_expected": 4.9999999982619014,
            "repairers_utilization": 0.9999999996523803
          },
          "fixed_parameters": {},
          "truncation": null,
          "diagnostics": {
            "queue_exists_probability_state": 0.9999999951633868,
            "waiting_probability_interpretation": "arrival_weighted_probability_for_new_breakdown"
          }
        },
        {
          "x_value": 6,
          "status": "ok",
          "regime": {
            "status": "ok",
            "is_stationary": true,
            "reason": null
          },
          "metrics": {
            "idle_machines_expected": 27.304348911284187,
            "waiting_machines_expected": 21.304349386703926,
            "waiting_probability": 0.9999990715138093,
            "busy_repairers_expected": 5.999999524580261,
            "repairers_utilization": 0.9999999207633768
          },
          "fixed_parameters": {},
          "truncation": null,
          "diagnostics": {
            "queue_exists_probability_state": 0.9999989922772596,
            "waiting_probability_interpretation": "arrival_weighted_probability_for_new_breakdown"
          }
        },
        {
          "x_value": 7,
          "status": "ok",
          "regime": {
            "status": "ok",
            "is_stationary": true,
            "reason": null
          },
          "metrics": {
            "idle_machines_expected": 25.02181523822872,
            "waiting_machines_expected": 18.021848580690826,
            "waiting_probability": 0.9999497065590499,
            "busy_repairers_expected": 6.999966657537895,
            "repairers_utilization": 0.9999952367911279
          },
          "fixed_parameters": {},
          "truncation": null,
          "diagnostics": {
            "queue_exists_probability_state": 0.9999449435897358,
            "waiting_probability_interpretation": "arrival_weighted_probability_for_new_breakdown"
          }
        },
        {
          "x_value": 8,
          "status": "ok",
          "regime": {
            "status": "ok",
            "is_stationary": true,
            "reason": null
          },
          "metrics": {
            "idle_machines_expected": 22.741059395576833,
            "waiting_machines_expected": 14.741904464115255,
            "waiting_probability": 0.9990024745703576,
            "busy_repairers_expected": 7.999154931461578,
            "repairers_utilization": 0.9998943664326972
          },
          "fixed_parameters": {},
          "truncation": null,
          "diagnostics": {
            "queue_exists_probability_state": 0.9988969463752245,
            "waiting_probability_interpretation": "arrival_weighted_probability_for_new_breakdown"
          }
        },
        {
          "x_value": 9,
          "status": "ok",
          "regime": {
            "status": "ok",
            "is_stationary": true,
            "reason": null
          },
          "metrics": {
            "idle_machines_expected": 20.478668871205205,
            "waiting_machines_expected": 11.488371424304624,
            "waiting_probability": 0.9909605487977968,
            "busy_repairers_expected": 8.990297446900579,
            "repairers_utilization": 0.9989219385445087
          },
          "fixed_parameters": {},
          "truncation": null,
          "diagnostics": {
            "queue_exists_probability_state": 0.9898922324262255,
            "waiting_probability_interpretation": "arrival_weighted_probability_for_new_breakdown"
          }
        },
        {
          "x_value": 10,
          "status": "ok",
          "regime": {
            "status": "ok",
            "is_stationary": true,
            "reason": null
          },
          "metrics": {
            "idle_machines_expected": 18.309455581051218,
            "waiting_machines_expected": 8.368836121321275,
            "waiting_probability": 0.9559902405620553,
            "busy_repairers_expected": 9.940619459729945,
            "repairers_utilization": 0.9940619459729945
          },
          "fixed_parameters": {},
          "truncation": null,
          "diagnostics": {
            "queue_exists_probability_state": 0.9503135188643078,
            "waiting_probability_interpretation": "arrival_weighted_probability_for_new_breakdown"
          }
        },
        {
          "x_value": 11,
          "status": "ok",
          "regime": {
            "status": "ok",
            "is_stationary": true,
            "reason": null
          },
          "metrics": {
            "idle_machines_expected": 16.396778224963768,
            "waiting_machines_expected": 5.6182239235193245,
            "waiting_probability": 0.8679890686633835,
            "busy_repairers_expected": 10.778554301444444,
            "repairers_utilization": 0.9798685728585859
          },
          "fixed_parameters": {},
          "truncation": null,
          "diagnostics": {
            "queue_exists_probability_state": 0.8505152099680429,
            "waiting_probability_interpretation": "arrival_weighted_probability_for_new_breakdown"
          }
        },
        {
          "x_value": 12,
          "status": "ok",
          "regime": {
            "status": "ok",
            "is_stationary": true,
            "reason": null
          },
          "metrics": {
            "idle_machines_expected": 14.906612015765083,
            "waiting_machines_expected": 3.475222994100258,
            "waiting_probability": 0.7235330753257457,
            "busy_repairers_expected": 11.431389021664824,
            "repairers_utilization": 0.952615751805402
          },
          "fixed_parameters": {},
          "truncation": null,
          "diagnostics": {
            "queue_exists_probability_state": 0.6892490045075097,
            "waiting_probability_interpretation": "arrival_weighted_probability_for_new_breakdown"
          }
        },
        {
          "x_value": 13,
          "status": "ok",
          "regime": {
            "status": "ok",
            "is_stationary": true,
            "reason": null
          },
          "metrics": {
            "idle_machines_expected": 13.882351107587008,
            "waiting_machines_expected": 2.0022382594822674,
            "waiting_probability": 0.550077482460844,
            "busy_repairers_expected": 11.88011284810474,
            "repairers_utilization": 0.9138548344695955
          },
          "fixed_parameters": {},
          "truncation": null,
          "diagnostics": {
            "queue_exists_probability_state": 0.5026909666797064,
            "waiting_probability_interpretation": "arrival_weighted_probability_for_new_breakdown"
          }
        },
        {
          "x_value": 14,
          "status": "ok",
          "regime": {
            "status": "ok",
            "is_stationary": true,
            "reason": null
          },
          "metrics": {
            "idle_machines_expected": 13.245746483801323,
            "waiting_machines_expected": 1.0867401814666624,
            "waiting_probability": 0.3829235698795718,
            "busy_repairers_expected": 12.15900630233466,
            "repairers_utilization": 0.8685004501667615
          },
          "fixed_parameters": {},
          "truncation": null,
          "diagnostics": {
            "queue_exists_probability_state": 0.33256929281987146,
            "waiting_probability_interpretation": "arrival_weighted_probability_for_new_breakdown"
          }
        },
        {
          "x_value": 15,
          "status": "ok",
          "regime": {
            "status": "ok",
            "is_stationary": true,
            "reason": null
          },
          "metrics": {
            "idle_machines_expected": 12.878735614446612,
            "waiting_machines_expected": 0.5589435979184596,
            "waiting_probability": 0.24534689177572222,
            "busy_repairers_expected": 12.319792016528153,
            "repairers_utilization": 0.8213194677685435
          },
          "fixed_parameters": {},
          "truncation": null,
          "diagnostics": {
            "queue_exists_probability_state": 0.2015081785719026,
            "waiting_probability_interpretation": "arrival_weighted_probability_for_new_breakdown"
          }
        },
        {
          "x_value": 16,
          "status": "ok",
          "regime": {
            "status": "ok",
            "is_stationary": true,
            "reason": null
          },
          "metrics": {
            "idle_machines_expected": 12.67957311033595,
            "waiting_machines_expected": 0.2725289491497944,
            "waiting_probability": 0.14510814453959273,
            "busy_repairers_expected": 12.407044161186155,
            "repairers_utilization": 0.7754402600741347
          },
          "fixed_parameters": {},
          "truncation": null,
          "diagnostics": {
            "queue_exists_probability_state": 0.11252269734065694,
            "waiting_probability_interpretation": "arrival_weighted_probability_for_new_breakdown"
          }
        },
        {
          "x_value": 17,
          "status": "ok",
          "regime": {
            "status": "ok",
            "is_stationary": true,
            "reason": null
          },
          "metrics": {
            "idle_machines_expected": 12.577395039063282,
            "waiting_machines_expected": 0.1255871514148141,
            "waiting_probability": 0.07926224085591772,
            "busy_repairers_expected": 12.451807887648467,
            "repairers_utilization": 0.7324592875087333
          },
          "fixed_parameters": {},
          "truncation": null,
          "diagnostics": {
            "queue_exists_probability_state": 0.05805636446367112,
            "waiting_probability_interpretation": "arrival_weighted_probability_for_new_breakdown"
          }
        },
        {
          "x_value": 18,
          "status": "ok",
          "regime": {
            "status": "ok",
            "is_stationary": true,
            "reason": null
          },
          "metrics": {
            "idle_machines_expected": 12.527926742905379,
            "waiting_machines_expected": 0.05444703027344883,
            "waiting_probability": 0.03994341359359561,
            "busy_repairers_expected": 12.47347971263193,
            "repairers_utilization": 0.6929710951462184
          },
          "fixed_parameters": {},
          "truncation": null,
          "diagnostics": {
            "queue_exists_probability_state": 0.0276796310618323,
            "waiting_probability_interpretation": "arrival_weighted_probability_for_new_breakdown"
          }
        },
        {
          "x_value": 19,
          "status": "ok",
          "regime": {
            "status": "ok",
            "is_stationary": true,
            "reason": null
          },
          "metrics": {
            "idle_machines_expected": 12.505431601227626,
            "waiting_machines_expected": 0.02209687414639486,
            "waiting_probability": 0.01853633869113044,
            "busy_repairers_expected": 12.483334727081232,
            "repairers_utilization": 0.6570176172148017
          },
          "fixed_parameters": {},
          "truncation": null,
          "diagnostics": {
            "queue_exists_probability_state": 0.012178701078733057,
            "waiting_probability_interpretation": "arrival_weighted_probability_for_new_breakdown"
          }
        },
        {
          "x_value": 20,
          "status": "ok",
          "regime": {
            "status": "ok",
            "is_stationary": true,
            "reason": null
          },
          "metrics": {
            "idle_machines_expected": 12.495875640653317,
            "waiting_machines_expected": 0.008354492749055097,
            "waiting_probability": 0.007904315811577668,
            "busy_repairers_expected": 12.487521147904262,
            "repairers_utilization": 0.6243760573952131
          },
          "fixed_parameters": {},
          "truncation": null,
          "diagnostics": {
            "queue_exists_probability_state": 0.004935265542839509,
            "waiting_probability_interpretation": "arrival_weighted_probability_for_new_breakdown"
          }
        },
        {
          "x_value": 21,
          "status": "ok",
          "regime": {
            "status": "ok",
            "is_stationary": true,
            "reason": null
          },
          "metrics": {
            "idle_machines_expected": 12.492103385112372,
            "waiting_machines_expected": 0.002929630018741763,
            "waiting_probability": 0.0030902565160616795,
            "busy_repairers_expected": 12.48917375509363,
            "repairers_utilization": 0.5947225597663633
          },
          "fixed_parameters": {},
          "truncation": null,
          "diagnostics": {
            "queue_exists_probability_state": 0.0018378452655668858,
            "waiting_probability_interpretation": "arrival_weighted_probability_for_new_breakdown"
          }
        },
        {
          "x_value": 22,
          "status": "ok",
          "regime": {
            "status": "ok",
            "is_stationary": true,
            "reason": null
          },
          "metrics": {
            "idle_machines_expected": 12.49072609599311,
            "waiting_machines_expected": 0.0009489570948545594,
            "waiting_probability": 0.001105185880955861,
            "busy_repairers_expected": 12.489777138898257,
            "repairers_utilization": 0.5677171426771935
          },
          "fixed_parameters": {},
          "truncation": null,
          "diagnostics": {
            "queue_exists_probability_state": 0.0006274329704634383,
            "waiting_probability_interpretation": "arrival_weighted_probability_for_new_breakdown"
          }
        },
        {
          "x_value": 23,
          "status": "ok",
          "regime": {
            "status": "ok",
            "is_stationary": true,
            "reason": null
          },
          "metrics": {
            "idle_machines_expected": 12.490262919717098,
            "waiting_machines_expected": 0.0002828654979207091,
            "waiting_probability": 0.00036072953025765875,
            "busy_repairers_expected": 12.489980054219178,
            "repairers_utilization": 0.5430426110530078
          },
          "fixed_parameters": {},
          "truncation": null,
          "diagnostics": {
            "queue_exists_probability_state": 0.00019589150599504395,
            "waiting_probability_interpretation": "arrival_weighted_probability_for_new_breakdown"
          }
        },
        {
          "x_value": 24,
          "status": "ok",
          "regime": {
            "status": "ok",
            "is_stationary": true,
            "reason": null
          },
          "metrics": {
            "idle_machines_expected": 12.490119982648515,
            "waiting_machines_expected": 7.730838024593695e-05,
            "waiting_probability": 0.0001071924524017736,
            "busy_repairers_expected": 12.49004267426827,
            "repairers_utilization": 0.5204184447611779
          },
          "fixed_parameters": {},
          "truncation": null,
          "diagnostics": {
            "queue_exists_probability_state": 5.5784929369067605e-05,
            "waiting_probability_interpretation": "arrival_weighted_probability_for_new_breakdown"
          }
        },
        {
          "x_value": 25,
          "status": "ok",
          "regime": {
            "status": "ok",
            "is_stationary": true,
            "reason": null
          },
          "metrics": {
            "idle_machines_expected": 12.490079646521217,
            "waiting_machines_expected": 1.9301187652909034e-05,
            "waiting_probability": 2.8920223525892058e-05,
            "busy_repairers_expected": 12.490060345333564,
            "repairers_utilization": 0.4996024138133426
          },
          "fixed_parameters": {},
          "truncation": null,
          "diagnostics": {
            "queue_exists_probability_state": 1.4448613481557089e-05,
            "waiting_probability_interpretation": "arrival_weighted_probability_for_new_breakdown"
          }
        },
        {
          "x_value": 26,
          "status": "ok",
          "regime": {
            "status": "ok",
            "is_stationary": true,
            "reason": null
          },
          "metrics": {
            "idle_machines_expected": 12.490069274292814,
            "waiting_machines_expected": 4.3849353784685e-06,
            "waiting_probability": 7.062360589969937e-06,
            "busy_repairers_expected": 12.490064889357434,
            "repairers_utilization": 0.48038711112913207
          },
          "fixed_parameters": {},
          "truncation": null,
          "diagnostics": {
            "queue_exists_probability_state": 3.3926670015678913e-06,
            "waiting_probability_interpretation": "arrival_weighted_probability_for_new_breakdown"
          }
        },
        {
          "x_value": 27,
          "status": "ok",
          "regime": {
            "status": "ok",
            "is_stationary": true,
            "reason": null
          },
          "metrics": {
            "idle_machines_expected": 12.490066852832516,
            "waiting_machines_expected": 9.026448547531088e-07,
            "waiting_probability": 1.5554162478013587e-06,
            "busy_repairers_expected": 12.490065950187661,
            "repairers_utilization": 0.46259503519213563
          },
          "fixed_parameters": {},
          "truncation": null,
          "diagnostics": {
            "queue_exists_probability_state": 7.195278338900891e-07,
            "waiting_probability_interpretation": "arrival_weighted_probability_for_new_breakdown"
          }
        },
        {
          "x_value": 28,
          "status": "ok",
          "regime": {
            "status": "ok",
            "is_stationary": true,
            "reason": null
          },
          "metrics": {
            "idle_machines_expected": 12.490066341679269,
            "waiting_machines_expected": 1.675578025024425e-07,
            "waiting_probability": 3.0764403530665895e-07,
            "busy_repairers_expected": 12.490066174121466,
            "repairers_utilization": 0.4460737919329095
          },
          "fixed_parameters": {},
          "truncation": null,
          "diagnostics": {
            "queue_exists_probability_state": 1.372319413947832e-07,
            "waiting_probability_interpretation": "arrival_weighted_probability_for_new_breakdown"
          }
        },
        {
          "x_value": 29,
          "status": "ok",
          "regime": {
            "status": "ok",
            "is_stationary": true,
            "reason": null
          },
          "metrics": {
            "idle_machines_expected": 12.49006624456187,
            "waiting_machines_expected": 2.7893734671304775e-08,
            "waiting_probability": 5.436943494400439e-08,
            "busy_repairers_expected": 12.490066216668135,
            "repairers_utilization": 0.43069193850579773
          },
          "fixed_parameters": {},
          "truncation": null,
          "diagnostics": {
            "queue_exists_probability_state": 2.3416477331498112e-08,
            "waiting_probability_interpretation": "arrival_weighted_probability_for_new_breakdown"
          }
        },
        {
          "x_value": 30,
          "status": "ok",
          "regime": {
            "status": "ok",
            "is_stationary": true,
            "reason": null
          },
          "metrics": {
            "idle_machines_expected": 12.490066228042505,
            "waiting_machines_expected": 4.137315522951966e-09,
            "waiting_probability": 8.533158449721885e-09,
            "busy_repairers_expected": 12.490066223905188,
            "repairers_utilization": 0.4163355407968396
          },
          "fixed_parameters": {},
          "truncation": null,
          "diagnostics": {
            "queue_exists_probability_state": 3.552657137870083e-09,
            "waiting_probability_interpretation": "arrival_weighted_probability_for_new_breakdown"
          }
        },
        {
          "x_value": 31,
          "status": "ok",
          "regime": {
            "status": "ok",
            "is_stationary": true,
            "reason": null
          },
          "metrics": {
            "idle_machines_expected": 12.490066225542812,
            "waiting_machines_expected": 5.425181999933142e-10,
            "waiting_probability": 1.1805134017701135e-09,
            "busy_repairers_expected": 12.490066225000293,
            "repairers_utilization": 0.4029053620967836
          },
          "fixed_parameters": {},
          "truncation": null,
          "diagnostics": {
            "queue_exists_probability_state": 4.756351796002934e-10,
            "waiting_probability_interpretation": "arrival_weighted_probability_for_new_breakdown"
          }
        },
        {
          "x_value": 32,
          "status": "ok",
          "regime": {
            "status": "ok",
            "is_stationary": true,
            "reason": null
          },
          "metrics": {
            "idle_machines_expected": 12.490066225208881,
            "waiting_machines_expected": 6.229540955754671e-11,
            "waiting_probability": 1.42634303105511e-10,
            "busy_repairers_expected": 12.490066225146586,
            "repairers_utilization": 0.3903145695358308
          },
          "fixed_parameters": {},
          "truncation": null,
          "diagnostics": {
            "queue_exists_probability_state": 5.5672246617670734e-11,
            "waiting_probability_interpretation": "arrival_weighted_probability_for_new_breakdown"
          }
        },
        {
          "x_value": 33,
          "status": "ok",
          "regime": {
            "status": "ok",
            "is_stationary": true,
            "reason": null
          },
          "metrics": {
            "idle_machines_expected": 12.490066225169867,
            "waiting_machines_expected": 6.189858391292684e-12,
            "waiting_probability": 1.4876906039719797e-11,
            "busy_repairers_expected": 12.490066225163678,
            "repairers_utilization": 0.37848685530799026
          },
          "fixed_parameters": {},
          "truncation": null,
          "diagnostics": {
            "queue_exists_probability_state": 5.6307133836859925e-12,
            "waiting_probability_interpretation": "arrival_weighted_probability_for_new_breakdown"
          }
        },
        {
          "x_value": 34,
          "status": "ok",
          "regime": {
            "status": "ok",
            "is_stationary": true,
            "reason": null
          },
          "metrics": {
            "idle_machines_expected": 12.49006622516593,
            "waiting_machines_expected": 5.241821103194462e-13,
            "waiting_probability": 1.3195430903376898e-12,
            "busy_repairers_expected": 12.490066225165405,
            "repairers_utilization": 0.3673548889754531
          },
          "fixed_parameters": {},
          "truncation": null,
          "diagnostics": {
            "queue_exists_probability_state": 4.847406054493283e-13,
            "waiting_probability_interpretation": "arrival_weighted_probability_for_new_breakdown"
          }
        },
        {
          "x_value": 35,
          "status": "ok",
          "regime": {
            "status": "ok",
            "is_stationary": true,
            "reason": null
          },
          "metrics": {
            "idle_machines_expected": 12.49006622516559,
            "waiting_machines_expected": 3.707984862181545e-14,
            "waiting_probability": 9.756983531753435e-14,
            "busy_repairers_expected": 12.490066225165553,
            "repairers_utilization": 0.3568590350047301
          },
          "fixed_parameters": {},
          "truncation": null,
          "diagnostics": {
            "queue_exists_probability_state": 3.481867727698574e-14,
            "waiting_probability_interpretation": "arrival_weighted_probability_for_new_breakdown"
          }
        },
        {
          "x_value": 36,
          "status": "ok",
          "regime": {
            "status": "ok",
            "is_stationary": true,
            "reason": null
          },
          "metrics": {
            "idle_machines_expected": 12.490066225165567,
            "waiting_machines_expected": 2.131292818545184e-15,
            "waiting_probability": 5.851338292934505e-15,
            "busy_repairers_expected": 12.490066225165563,
            "repairers_utilization": 0.34694628403237676
          },
          "fixed_parameters": {},
          "truncation": null,
          "diagnostics": {
            "queue_exists_probability_state": 2.0301000773499776e-15,
            "waiting_probability_interpretation": "arrival_weighted_probability_for_new_breakdown"
          }
        },
        {
          "x_value": 37,
          "status": "ok",
          "regime": {
            "status": "ok",
            "is_stationary": true,
            "reason": null
          },
          "metrics": {
            "idle_machines_expected": 12.490066225165563,
            "waiting_machines_expected": 9.560808052469099e-17,
            "waiting_probability": 2.734025414360923e-16,
            "busy_repairers_expected": 12.490066225165563,
            "repairers_utilization": 0.33756935743690714
          },
          "fixed_parameters": {},
          "truncation": null,
          "diagnostics": {
            "queue_exists_probability_state": 9.229232023419906e-17,
            "waiting_probability_interpretation": "arrival_weighted_probability_for_new_breakdown"
          }
        },
        {
          "x_value": 38,
          "status": "ok",
          "regime": {
            "status": "ok",
            "is_stationary": true,
            "reason": null
          },
          "metrics": {
            "idle_machines_expected": 12.490066225165563,
            "waiting_machines_expected": 3.139673988897416e-18,
            "waiting_probability": 9.336967529485857e-18,
            "busy_repairers_expected": 12.490066225165563,
            "repairers_utilization": 0.3286859532938306
          },
          "fixed_parameters": {},
          "truncation": null,
          "diagnostics": {
            "queue_exists_probability_state": 3.068930073302601e-18,
            "waiting_probability_interpretation": "arrival_weighted_probability_for_new_breakdown"
          }
        },
        {
          "x_value": 39,
          "status": "ok",
          "regime": {
            "status": "ok",
            "is_stationary": true,
            "reason": null
          },
          "metrics": {
            "idle_machines_expected": 12.490066225165563,
            "waiting_machines_expected": 6.712372093027088e-20,
            "waiting_probability": 2.072899079365473e-19,
            "busy_repairers_expected": 12.490066225165563,
            "repairers_utilization": 0.32025810833757856
          },
          "fixed_parameters": {},
          "truncation": null,
          "diagnostics": {
            "queue_exists_probability_state": 6.638627379322944e-20,
            "waiting_probability_interpretation": "arrival_weighted_probability_for_new_breakdown"
          }
        },
        {
          "x_value": 40,
          "status": "ok",
          "regime": {
            "status": "ok",
            "is_stationary": true,
            "reason": null
          },
          "metrics": {
            "idle_machines_expected": 12.490066225165563,
            "waiting_machines_expected": 7.010356846500078e-22,
            "waiting_probability": 2.245098375019113e-21,
            "busy_repairers_expected": 12.490066225165563,
            "repairers_utilization": 0.3122516556291391
          },
          "fixed_parameters": {},
          "truncation": null,
          "diagnostics": {
            "queue_exists_probability_state": 7.010356846500078e-22,
            "waiting_probability_interpretation": "arrival_weighted_probability_for_new_breakdown"
          }
        },
        {
          "x_value": 41,
          "status": "ok",
          "regime": {
            "status": "ok",
            "is_stationary": true,
            "reason": null
          },
          "metrics": {
            "idle_machines_expected": 12.490066225165563,
            "waiting_machines_expected": 0.0,
            "waiting_probability": 0.0,
            "busy_repairers_expected": 12.490066225165563,
            "repairers_utilization": 0.304635761589404
          },
          "fixed_parameters": {},
          "truncation": null,
          "diagnostics": {
            "queue_exists_probability_state": 0,
            "waiting_probability_interpretation": "arrival_weighted_probability_for_new_breakdown"
          }
        }
      ],
      "notes": [
        "Состояние = число неисправных станков.",
        "waiting_probability трактуется как вероятность того, что новый отказ поступит в систему, где все наладчики уже заняты."
      ],
      "summary": {
        "repairers_range": [
          1,
          41
        ]
      }
    }
  ],
  "summary": {
    "repairers_range": [
      1,
      41
    ]
  }
}
